jaanca_datetime/__init__.py
jaanca_datetime/utils/__init__.py
jaanca_datetime/utils/helpers/__init__.py
jaanca_datetime/utils/helpers/datetime_helper.py
jaanca_datetime-0.1.2.dist-info/LICENSE.txt
jaanca_datetime-0.1.2.dist-info/METADATA
jaanca_datetime-0.1.2.dist-info/WHEEL
jaanca_datetime-0.1.2.dist-info/top_level.txt
jaanca_datetime-0.1.2.dist-info/RECORD
